flybehavior_response/__init__.py
flybehavior_response/cli.py
flybehavior_response/config.py
flybehavior_response/evaluate.py
flybehavior_response/features.py
flybehavior_response/io.py
flybehavior_response/io_wide.py
flybehavior_response/logging_utils.py
flybehavior_response/modeling.py
flybehavior_response/prepare_raw.py
flybehavior_response/train.py
flybehavior_response/visualize.py
flybehavior_response/weights.py
flybehavior_response/tests/test_prepare_raw.py
flybehavior_response/tests/test_response_cli.py
flybehavior_response/tests/test_response_io.py
flybehavior_response/tests/test_response_pipelines.py
flypca/__init__.py
flypca/cli.py
flypca/cluster.py
flypca/features.py
flypca/io.py
flypca/lagpca.py
flypca/preprocess.py
flypca/synthetic.py
flypca/viz.py
flybehavior_response-0.1.0.dist-info/METADATA
flybehavior_response-0.1.0.dist-info/WHEEL
flybehavior_response-0.1.0.dist-info/entry_points.txt
flybehavior_response-0.1.0.dist-info/RECORD
