Metadata-Version: 2.4
Name: flybehavior-response
Version: 0.1.0
Summary: CLI and helpers for scoring Drosophila proboscis responses from envelope or raw coordinate data.
Project-URL: Homepage, https://notReal.com
Author-email: Cole Hanan <cole.hanan11@gmail.com>
License: MIT
Classifier: Operating System :: OS Independent
Classifier: Programming Language :: Python :: 3
Requires-Python: >=3.11
Requires-Dist: hdbscan<0.9,>=0.8
Requires-Dist: joblib<1.6,>=1.2
Requires-Dist: matplotlib<3.10,>=3.6
Requires-Dist: numpy<2.0,>=1.23
Requires-Dist: pandas<3.0,>=1.5
Requires-Dist: pyyaml<7.0,>=6.0
Requires-Dist: scikit-learn<1.5,>=1.2
Requires-Dist: scipy<1.13,>=1.9
Requires-Dist: typer[all]<1.0,>=0.9
Requires-Dist: umap-learn<0.6,>=0.5
